README.md
setup.py
pelican_jsmath/__init__.py
pelican_jsmath/jsmath.py
pelican_jsmath/jsmath_markdown_extension.py
pelican_jsmath.egg-info/PKG-INFO
pelican_jsmath.egg-info/SOURCES.txt
pelican_jsmath.egg-info/dependency_links.txt
pelican_jsmath.egg-info/top_level.txt