Metadata-Version: 1.0
Name: pelican-jsmath
Version: 0.1.0
Summary: Pelican Plugin that passes math to JavaScript.
Home-page: http://github.com/svenkreiss/pelican-jsmath
Author: Sven Kreiss
Author-email: me@svenkreiss.com
License: AGPL-3.0
Platform: UNKNOWN
